wtu_mlflow/__init__.py
wtu_mlflow/annotation.py
wtu_mlflow/base_mlflow_client.py
wtu_mlflow/env_checker.py
wtu_mlflow/mlflow_client.py
wtu_mlflow/onnx_client.py
wtu_mlflow/schema.py
wtu_mlflow/torch_client.py
wtu_mlflow/triton_python_backend_utils.py
wtu_mlflow-0.1.9.dist-info/METADATA
wtu_mlflow-0.1.9.dist-info/WHEEL
wtu_mlflow-0.1.9.dist-info/top_level.txt
wtu_mlflow-0.1.9.dist-info/RECORD
