Metadata-Version: 2.1
Name: wtu-mlflow
Version: 0.1.9
Summary: W-Train Utils for MLflow
Home-page: https://github.com/WIM-Corporation/w-train-utils-mlflow
Author: hbjs
Author-email: hbjs97@naver.com
License: UNKNOWN
Platform: UNKNOWN
Classifier: Programming Language :: Python :: 3.7
Classifier: License :: OSI Approved :: MIT License
Requires-Python: >=3.7
Requires-Dist: mlflow ==1.30.1
Requires-Dist: numpy >=1.21.6
Requires-Dist: boto3 >=1.24.0
Requires-Dist: pika >=0.13.0
Requires-Dist: onnx
Requires-Dist: onnxruntime
